mem0_mcp_server/__init__.py
mem0_mcp_server/config.json
mem0_mcp_server/http_entry.py
mem0_mcp_server/mcp.json
mem0_mcp_server/py.typed
mem0_mcp_server/schemas.py
mem0_mcp_server/server.py
mem0_mcp_server-0.2.1.data/data/mem0_mcp_server/py.typed
mem0_mcp_server-0.2.1.data/data/share/mcp/configs/mem0-mcp-server.json
mem0_mcp_server-0.2.1.data/data/share/mcp/servers/mem0-mcp-server.json
mem0_mcp_server-0.2.1.dist-info/METADATA
mem0_mcp_server-0.2.1.dist-info/WHEEL
mem0_mcp_server-0.2.1.dist-info/entry_points.txt
mem0_mcp_server-0.2.1.dist-info/licenses/LICENSE
mem0_mcp_server-0.2.1.dist-info/RECORD
