Metadata-Version: 2.4
Name: mem0-mcp-server
Version: 0.2.1
Summary: Model Context Protocol server that exposes the Mem0 long-term memory API as tools
Project-URL: Homepage, https://mem0.ai
Project-URL: Repository, https://github.com/mem0-ai/mem0-mcp-server
Project-URL: Documentation, https://docs.mem0.ai
Author: Mem0
License: Apache-2.0
License-File: LICENSE
Keywords: agents,anthropic,claude,llm,mcp,mem0,memory,tooling
Classifier: Intended Audience :: Developers
Classifier: License :: OSI Approved :: Apache Software License
Classifier: Operating System :: OS Independent
Classifier: Programming Language :: Python
Classifier: Programming Language :: Python :: 3
Classifier: Programming Language :: Python :: 3.10
Classifier: Programming Language :: Python :: 3.11
Classifier: Programming Language :: Python :: 3.12
Classifier: Topic :: Software Development :: Libraries
Classifier: Typing :: Typed
Requires-Python: >=3.10
Requires-Dist: mcp[cli]>=1.6.0
Requires-Dist: mem0ai>=1.0.1
Requires-Dist: pydantic-ai-slim[mcp]>=1.14.1
Requires-Dist: python-dotenv>=1.2.1
Requires-Dist: requests>=2.32.5
Requires-Dist: smithery>=0.4.2
Provides-Extra: agent
Requires-Dist: pydantic-ai-slim[mcp]>=1.14.1; extra == 'agent'
Requires-Dist: python-dotenv>=1.2.1; extra == 'agent'
